irv/__init__.py
irv/__main__.py
irv/irv.py
irv/mainwindow.py
irv-0.0.7.dist-info/LICENSE
irv-0.0.7.dist-info/METADATA
irv-0.0.7.dist-info/WHEEL
irv-0.0.7.dist-info/top_level.txt
irv-0.0.7.dist-info/RECORD
