Metadata-Version: 2.1
Name: irv
Version: 0.0.7
Summary: ISMRMRD rawdata view and analysis tools
Home-page: https://github.com/medlab/ismrmrd-rawdata-viewer
Author: Cong Zhang
Author-email: congzhangzh@gmail.com
Maintainer: Cong Zhang
Maintainer-email: congzhangzh@gmail.com
License: UNKNOWN
Platform: UNKNOWN
Classifier: License :: OSI Approved :: MIT License
Classifier: Programming Language :: Python :: 3
Classifier: Operating System :: OS Independent
Requires-Dist: PySide6
Requires-Dist: matplotlibqml
